[{"code":"001740","date":"2026-06-25","company_name":"SK네트웍스","article_title":"엔코아 AI캠퍼스, 실무형 AI인재 양성코스 7월 개강","briefing":"SK네트웍스의 주가가 13.33% 상승하여 10,800원에 마감되었습니다. 이 상승은 자회사 엔코아의 AI 인재 양성 교육 프로그램 개강 소식과 관련이 있을 것으로 보입니다. 이러한 교육 프로그램은 SK네트웍스의 미래 성장 가능성을 높이는 긍정적인 요소로 작용할 것으로 기대됩니다.","content_url":"https://www.dt.co.kr/article/12069411","publisher":"디지털타임스","polarity":null,"change_rate":13.33,"created_at":"2026-06-24T21:48:00.000000"},{"code":"001740","date":"2026-06-22","company_name":"SK네트웍스","article_title":"엔코아, 유니온시스템즈와 '데이터웨어' 전제품 총판 협약 체결","briefing":"SK네트웍스의 주가가 2.68% 하락하여 10,150원에 마감되었습니다. 이번 하락은 특별한 이유가 없지만, SK하이닉스의 주가 상승과 관련된 시장의 전반적인 흐름 속에서 영향을 받은 것으로 보입니다. 또한, SK네트웍스의 자회사인 엔코아의 데이터 통합관리 솔루션 총판 협약 체결 소식이 있었으나, 주가에 긍정적인 영향을 미치지 못한 것으로 판단됩니다.","content_url":"https://www.edaily.co.kr/news/newspath.asp?newsid=05047926645483032","publisher":"이데일리","polarity":null,"change_rate":-2.68,"created_at":"2026-06-18T15:57:00.000000"},{"code":"001740","date":"2026-06-12","company_name":"SK네트웍스","article_title":"SK네트웍스 ‘AI 컴퍼니’ 전환 가속…성장 동력 확보 속도","briefing":"SK네트웍스의 주가가 11.40% 상승하여 13,000원에 마감되었습니다. 이 상승은 SK네트웍스가 인공지능(AI) 중심의 사업지주회사로 전환하고, AI 기반 서비스 고도화에 집중하고 있다는 소식에 힘입은 것으로 보입니다. 또한, SK그룹과 엔비디아의 협력 소식이 시장의 긍정적인 반응을 이끌어낸 것으로 분석됩니다.","content_url":"https://www.segye.com/newsView/20260611515443","publisher":"세계일보","polarity":"긍정","change_rate":11.4,"created_at":"2026-06-12T06:03:00.000000"},{"code":"001740","date":"2026-06-10","company_name":"SK네트웍스","article_title":"젠슨 황 방한 효과 하루 만에 반전…네이버·LG전자 등 동반 급락","briefing":"SK네트웍스의 주가가 9.38% 하락하여 12,950원에 마감되었습니다. 이번 하락은 젠슨 황 엔비디아 CEO의 방한 이후 AI 관련 종목들이 차익 실현 매물에 의해 약세를 보인 것과 관련이 있습니다. 이러한 시장의 전반적인 하락세 속에서 SK네트웍스도 영향을 받은 것으로 분석됩니다.","content_url":"https://www.kado.net/news/articleView.html?idxno=2054756","publisher":"강원도민일보","polarity":null,"change_rate":-9.38,"created_at":"2026-06-09T16:25:10.000000"},{"code":"001740","date":"2026-06-09","company_name":"SK네트웍스","article_title":"젠슨 황 효과 이어간다…SK네트웍스·SKT 동반 강세","briefing":"SK네트웍스의 주가가 0.85% 상승하여 14,290원에 마감되었습니다. 주가는 SK그룹과 엔비디아의 AI 팩토리 구축 협력 소식에 긍정적인 반응을 보인 것으로 분석됩니다. 그러나 전체적인 주가 변동은 크지 않았으며, 시장의 전반적인 흐름과 관련된 주요 이슈가 있었습니다.","content_url":"https://www.mt.co.kr/stock/2026/06/09/2026060909144166222","publisher":"머투","polarity":null,"change_rate":0.85,"created_at":"2026-06-09T09:15:03.000000"},{"code":"001740","date":"2026-06-08","company_name":"SK네트웍스","article_title":"'AI 지주사' SK네트웍스, SK-엔비디아 'AI 동맹'에 상한가[핫종목]","briefing":"SK네트웍스의 주가가 30.00% 상승하여 14,170원에 마감되었습니다. 이 상승은 SK그룹과 엔비디아의 인공지능(AI) 팩토리 구축 협력 소식에 힘입은 것으로 보입니다. 이러한 협력은 SK네트웍스의 사업 확장과 성장 가능성을 높이는 긍정적인 요소로 작용하고 있습니다.","content_url":"https://www.news1.kr/finance/general-stock/6190694","publisher":"뉴스1","polarity":null,"change_rate":30.0,"created_at":"2026-06-08T14:30:48.000000"},{"code":"001740","date":"2026-06-05","company_name":"SK네트웍스","article_title":"반도체 급락에 매도 사이드카 발동…8100까지 밀린 코스피 [마켓 라이브]","briefing":"SK네트웍스의 주가가 16.22% 하락하여 10,900원에 마감되었습니다. 이번 하락은 반도체 업종의 급락과 관련이 있으며, 삼성전자와 SK하이닉스의 주가가 각각 5.62%와 7.35% 하락한 것이 주요 원인으로 작용했습니다. 이러한 시장 전반의 하락세가 SK네트웍스에도 부정적인 영향을 미친 것으로 분석됩니다.","content_url":"https://www.hankyung.com/article/202606058844i","publisher":"한국경제","polarity":null,"change_rate":-16.22,"created_at":"2026-06-05T09:21:00.000000"},{"code":"001740","date":"2026-06-04","company_name":"SK네트웍스","article_title":"SK스퀘어, 원스토어 매각 속도…리밸런싱 마무리 속 AI빅딜 조준[시그널]","briefing":"SK네트웍스의 주가가 1.32% 상승하여 13,010원에 마감되었습니다. 주가 상승의 주요 원인은 최근 증시 활황과 관련된 긍정적인 시장 분위기로 보입니다. 그러나 SK네트웍스와 직접적인 관련이 없는 LG전자의 목표주가 초과 소식이 보도되며 시장의 관심을 끌었습니다.","content_url":"https://www.sedaily.com/article/20050688","publisher":"서울경제","polarity":"중립","change_rate":1.32,"created_at":"2026-06-02T06:00:00.000000"},{"code":"001740","date":"2026-05-29","company_name":"SK네트웍스","article_title":"엔코아, 국가데이터처에 공공데이터 품질관리 고도화 방안 제시","briefing":"SK네트웍스의 주가가 5.84% 하락하여 11,280원에 마감되었습니다. 이번 하락은 반도체 대형주가 급등하는 가운데 SK네트웍스의 주가가 상대적으로 부진한 모습을 보였기 때문으로 분석됩니다. 그러나 SK네트웍스와 관련된 주요 이슈로는 자회사 엔코아의 공공데이터 품질관리 방안 제시가 있었습니다.","content_url":"https://www.dt.co.kr/article/12064592","publisher":"디지털타임스","polarity":null,"change_rate":-5.84,"created_at":"2026-05-27T17:16:00.000000"},{"code":"001740","date":"2026-05-27","company_name":"SK네트웍스","article_title":"[서울데이터랩]반도체 대형주 급등 속 거래대금 집중…SK네트웍스·삼화전자도 강세","briefing":"SK네트웍스의 주가가 4.21% 상승하여 11,380원에 마감되었습니다. 이번 상승은 반도체 대형주들의 강세와 함께 거래량이 증가한 데 따른 것으로 보입니다. 이러한 시장 분위기는 SK네트웍스의 주가에도 긍정적인 영향을 미친 것으로 분석됩니다.","content_url":"https://www.seoul.co.kr/news/economy/securities/2026/05/27/20260527500165","publisher":"서울신문","polarity":null,"change_rate":4.21,"created_at":"2026-05-27T14:26:00.000000"},{"code":"001740","date":"2026-05-26","company_name":"SK네트웍스","article_title":"“화요일엔 오후 10시까지”…SK스피드메이트, 야간특별운영","briefing":"SK네트웍스의 주가가 30.00% 상승하여 10,920원에 마감되었습니다. 이번 상승은 SK스피드메이트의 야간 특별 운영 서비스인 '별빛정비' 도입 소식에 기인한 것으로 보입니다. 여름철 고객 수요 증가에 따른 매출 성장 기대감이 주가에 긍정적인 영향을 미친 것으로 분석됩니다.","content_url":"https://www.sedaily.com/article/20048068","publisher":"서울경제","polarity":"중립","change_rate":30.0,"created_at":"2026-05-26T09:24:00.000000"},{"code":"001740","date":"2026-05-22","company_name":"SK네트웍스","article_title":"SK네트웍스, 로봇 사업 확장 기반 마련...목표가 ↑ -iM證","briefing":"SK네트웍스의 주가가 2.82% 상승하여 8,400원에 마감되었습니다. 이 상승은 웰니스 로봇 출시와 워커힐 부문의 수익성 개선에 대한 긍정적인 전망에 기인한 것으로 보입니다. 특히, 1분기 영업이익이 전년 대비 109.4% 증가한 점이 실적 개선에 긍정적인 영향을 미쳤습니다.","content_url":"http://www.fnnews.com/news/202605180820434328","publisher":"파이낸셜뉴스","polarity":"긍정","change_rate":2.82,"created_at":"2026-05-18T09:04:00.000000"},{"code":"001740","date":"2026-05-15","company_name":"SK네트웍스","article_title":"SK네트웍스, 1분기 영업익 334억원⋯전년比 102% ↑","briefing":"SK네트웍스의 주가가 10.38% 상승하여 8,720원에 마감되었습니다. 이번 상승은 1분기 영업이익이 전년 대비 102% 증가한 호실적에 힘입은 것으로 분석됩니다. 또한, AI 기술 접목과 사업 모델 혁신을 지속적으로 추진하고 있다는 점이 긍정적인 영향을 미친 것으로 보입니다.","content_url":"http://www.inews24.com/view/1968649","publisher":"아이뉴스24","polarity":"긍정","change_rate":10.38,"created_at":"2026-05-15T07:49:00.000000"},{"code":"001740","date":"2026-05-14","company_name":"SK네트웍스","article_title":"SK네트웍스, 1분기 영업익 334억원… 전년比 102%↑","briefing":"SK네트웍스의 주가가 29.93% 상승하여 7,900원에 마감되었습니다. 이번 상승은 1분기 영업이익이 334억원으로 전년 대비 102% 증가한 호실적에 기인한 것으로 보입니다. 또한 AI 분야의 투자 성과와 신규 사업 모델 혁신 계획이 긍정적인 영향을 미쳤습니다.","content_url":"https://biz.chosun.com/industry/company/2026/05/14/K62P7ODVGVCBFM4GZUQ75VVSCI/?utm_medium=original&utm_campaign=biz","publisher":"조선비즈","polarity":"긍정","change_rate":29.93,"created_at":"2026-05-14T14:26:00.000000"}]