[{"code":"028100","date":"2026-06-10","company_name":"동아지질","article_title":"동아지질, 75억 규모 자사주 취득 신탁계약 체결","briefing":"동아지질의 주가가 1.28% 상승하여 14,220원에 마감되었습니다. 주가 상승의 주요 원인은 75억 원 규모의 자사주 취득 신탁계약 체결 소식으로, 이는 주가 안정 및 주주가치 제고를 위한 조치로 해석됩니다. 그러나 전체적인 변동률은 크지 않았으며, 향후 주가에 미치는 영향은 지켜봐야 할 것으로 보입니다.","content_url":"https://biz.heraldcorp.com/article/10768691","publisher":"헤럴드경제","polarity":"긍정","change_rate":1.28,"created_at":"2026-06-10T15:35:00.000000"},{"code":"028100","date":"2026-06-09","company_name":"동아지질","article_title":"동양제강·지비라이트 등 부산 명문향토기업 선정","briefing":"동아지질의 주가가 6.04% 상승하여 14,040원에 마감되었습니다. 이 상승은 부산시에서 동아지질을 명문향토기업으로 선정한 소식에 긍정적인 반응이 나타난 것으로 분석됩니다. 이러한 인식은 기업의 지역 내 위상 강화와 함께 향후 성장 가능성에 대한 기대감을 높이고 있습니다.","content_url":"http://www.kookje.co.kr/news2011/asp/newsbody.asp?code=0200&key=20260603.22011000062","publisher":"국제신문","polarity":null,"change_rate":6.04,"created_at":"2026-06-02T19:07:00.000000"},{"code":"028100","date":"2026-06-08","company_name":"동아지질","article_title":"부산 명문향토기업 33개사 선정… 세무 검사 3년 유예 파격 대우","briefing":"동아지질의 주가가 5.77% 하락하여 13,240원에 마감되었습니다. 이번 하락은 특별한 이유가 없으나, 부산시에서 동아지질을 포함한 명문향토기업으로 선정된 소식이 있었습니다. 이러한 선정은 기업의 이미지 개선에 기여할 수 있으나, 주가에는 즉각적인 긍정적 영향을 미치지 못한 것으로 보입니다.","content_url":"https://www.mk.co.kr/article/12062672","publisher":"매일경제","polarity":null,"change_rate":-5.77,"created_at":"2026-06-01T11:17:00.000000"}]