[{"code":"035420","date":"2026-06-15","company_name":"NAVER","article_title":"NAVER, 인프라 사업 확장 긍정적…목표가 30만3000원 상향-LS","briefing":"NAVER의 주가가 0.40% 상승하여 248,000원에 마감되었습니다. 주가는 인프라 사업 확장에 대한 긍정적인 평가와 목표가 상향 조정 소식에 힘입은 것으로 보입니다. 그러나 전반적인 시장 분위기와 차익 실현 매물로 인해 주가 변동이 크지 않았습니다.","content_url":"https://www.mt.co.kr/stock/2026/06/11/2026061107494862469","publisher":"머니투데이","polarity":null,"change_rate":0.4,"created_at":"2026-06-11T07:51:00.000000"},{"code":"035420","date":"2026-06-09","company_name":"NAVER","article_title":"NAVER, 엔비디아 협력에 증권가 목표가 줄상향에도 6%대 하락 '왜'[특징주]","briefing":"NAVER의 주가가 7.89% 하락하여 257,000원에 마감되었습니다. 이번 하락은 전일 급등에 따른 차익실현 매물이 쏟아진 결과로 분석됩니다. 또한, 인터넷 및 일부 자동차 부품주가 약세를 보이며 수급 쏠림 현상이 심화된 점도 영향을 미친 것으로 보입니다.","content_url":"https://www.edaily.co.kr/news/newspath.asp?newsid=03253766645480080","publisher":"이데일리","polarity":"긍정","change_rate":-7.89,"created_at":"2026-06-09T09:38:13.000000"},{"code":"035420","date":"2026-06-08","company_name":"NAVER","article_title":"Naver Cloud, Nvidia to unveil plans for joint AI factory initiative","briefing":"NAVER의 주가가 9.20% 상승하여 279,000원에 마감되었습니다. 이 상승은 엔비디아와의 AI 팩토리 공동 사업 협력 소식에 힘입은 것으로 보입니다. 이러한 협력 기대감이 NAVER의 신사업 확장에 긍정적인 영향을 미칠 것으로 전망됩니다.","content_url":"https://koreajoongangdaily.joins.com/news/2026-06-02/business/industry/Naver-Cloud-Nvidia-to-unveil-plans-for-joint-AI-factory-initiative/2606852","publisher":"중앙데일리","polarity":"중립","change_rate":9.2,"created_at":"2026-06-02T17:52:59.000000"}]