[{"code":"039840","date":"2026-06-16","company_name":"디오","article_title":"디오, 이란 제재 완화 및 동결자금 해제에 따른 이란향 임플란트 사업 정상화 기대","briefing":"디오의 주가가 0.22% 상승하여 13,460원에 마감되었습니다. 주가는 소폭 상승했지만, 이란 제재 완화에 따른 임플란트 사업 정상화 기대감이 주요 이슈로 작용하고 있습니다. 이란과의 관계 개선이 이루어질 경우, 디오는 현지 시장에서의 매출 회복이 가능할 것으로 전망됩니다.","content_url":"https://www.edaily.co.kr/news/newspath.asp?newsid=03237366645482376","publisher":"이데일리","polarity":null,"change_rate":0.22,"created_at":"2026-06-16T09:38:00.000000"},{"code":"039840","date":"2026-06-15","company_name":"디오","article_title":"가시화 되는 중동사태 종전…디오 \"이란 임플란트 시장 정상화 기대\"","briefing":"디오의 주가가 0.37% 상승하여 13,430원에 마감되었습니다. 주가는 미국과 이란의 종전 가능성에 따른 이란 임플란트 시장 정상화 기대감으로 인해 소폭 상승한 것으로 보입니다. 그러나 주가 변동이 크지 않았던 만큼, 향후 시장 반응을 지켜볼 필요가 있습니다.","content_url":"https://www.news1.kr/local/busan-gyeongnam/6197686","publisher":"뉴스1","polarity":null,"change_rate":0.37,"created_at":"2026-06-15T14:43:14.000000"},{"code":"039840","date":"2026-06-10","company_name":"디오","article_title":"인플루디오, ‘포카스팟’ 일본 시부야 신규 매장 오픈","briefing":"디오의 주가가 0.45% 상승하여 13,280원에 마감되었습니다. 이 상승은 일본 도쿄 시부야에 신규 매장을 오픈한 소식에 힘입은 것으로 보입니다. 해외 시장 확장을 통한 매출 증가 기대감이 주가에 긍정적인 영향을 미친 것으로 분석됩니다.","content_url":"http://www.wowtv.co.kr/NewsCenter/News/Read?articleId=A202606100335&t=NN","publisher":"한국경제TV","polarity":null,"change_rate":0.45,"created_at":"2026-06-10T11:02:00.000000"},{"code":"039840","date":"2026-06-08","company_name":"디오","article_title":"코앞 다가온 북중미 월드컵…  유통가, 응원 마케팅 총력전","briefing":"디오의 주가가 5.29% 하락하여 13,060원에 마감되었습니다. 이번 하락은 특별한 이유가 없지만, 최근 유통업계의 마케팅 활동과 관련된 뉴스가 있었음을 알 수 있습니다. 이러한 외부 요인들이 시장의 전반적인 분위기에 영향을 미쳤을 가능성이 있습니다.","content_url":"https://www.donga.com/news/Economy/article/all/20260608/134068468/1","publisher":"동아일보","polarity":"중립","change_rate":-5.29,"created_at":"2026-06-08T10:41:00.000000"}]