[{"code":"126340","date":"2026-06-19","company_name":"비나텍","article_title":"“전력기기株 다시 전류 통했나”…LS일렉 12%·효성重 8% 급등[이런국장 저런주식]","briefing":"비나텍의 주가가 5.18% 상승하여 121,800원에 마감되었습니다. 이 상승은 인공지능(AI) 데이터센터 확대에 따른 전력망 투자 기대감과 저가 매수세 유입에 힘입은 것으로 보입니다. 전력기기주 전반의 강세가 비나텍의 주가 상승에 긍정적인 영향을 미친 것으로 분석됩니다.","content_url":"https://www.sedaily.com/article/20057688","publisher":"서울경제","polarity":null,"change_rate":5.18,"created_at":"2026-06-19T09:50:00.000000"},{"code":"126340","date":"2026-06-18","company_name":"비나텍","article_title":"기업 공시[6월 17일]","briefing":"비나텍의 주가가 6.69% 하락하여 115,800원에 마감되었습니다. 이번 하락은 특별한 뉴스나 이슈가 없었으나, 최근 시장의 전반적인 불안정성과 관련된 우려가 작용했을 가능성이 있습니다. 이러한 상황 속에서도 비나텍은 여전히 기술력에 대한 긍정적인 평가를 받고 있습니다.","content_url":"https://www.sedaily.com/article/20056922","publisher":"서경","polarity":null,"change_rate":-6.69,"created_at":"2026-06-17T16:33:08.000000"},{"code":"126340","date":"2026-06-15","company_name":"비나텍","article_title":"테슬라·포르쉐도 베팅…AI 전력난이 밀어올린 태양광·수소株","briefing":"비나텍의 주가가 7.86% 상승하여 113,900원에 마감되었습니다. 이 상승은 AI 전력난과 관련하여 태양광 및 수소 관련 주식에 대한 투자 증가가 긍정적인 영향을 미친 것으로 보입니다. 이러한 시장의 관심은 비나텍의 성장 가능성을 높이고, 향후 실적 개선에 대한 기대감을 증대시킬 것으로 예상됩니다.","content_url":"https://www.hankyung.com/article/2026061237841","publisher":"한국경제","polarity":null,"change_rate":7.86,"created_at":"2026-06-13T06:01:00.000000"},{"code":"126340","date":"2026-06-08","company_name":"비나텍","article_title":"[서울데이터랩] 코스닥 7% 급락 출발…외국인 순매수에도 931.92 마감 수준까지 밀려","briefing":"비나텍의 주가가 12.91% 하락하여 105,900원에 마감되었습니다. 이번 하락은 코스닥 시장의 전반적인 급락과 관련이 있으며, 특히 개별 종목 수급 논란이 영향을 미친 것으로 보입니다. 이러한 시장 환경 속에서 비나텍의 주가는 부정적인 영향을 받았던 것으로 분석됩니다.","content_url":"https://www.seoul.co.kr/news/economy/securities/2026/06/08/20260608500023","publisher":"서울신문","polarity":null,"change_rate":-12.91,"created_at":"2026-06-08T09:23:00.000000"},{"code":"126340","date":"2026-06-02","company_name":"비나텍","article_title":"전북도, 비나텍 등 성장사다리 기업 50개 지정…맞춤형 지원","briefing":"비나텍의 주가가 1.35% 하락하여 131,100원에 마감되었습니다. 이 하락세는 특별한 직접적인 원인이 없으나, 전북도에서 비나텍을 포함한 성장사다리 기업으로 지정한 소식이 있었습니다. 이러한 지원이 기업에 긍정적인 영향을 미칠 수 있으나, 시장 반응은 미미했던 것으로 보입니다.","content_url":"https://www.yna.co.kr/view/AKR20260602069000055?input=1195m","publisher":"연합뉴스","polarity":"중립","change_rate":-1.35,"created_at":"2026-06-02T10:50:00.000000"},{"code":"126340","date":"2026-06-01","company_name":"비나텍","article_title":"정기변경 앞둔 코스피200·코스닥150…\"편입 종목 수급 주목\"","briefing":"비나텍의 주가가 10.81% 하락하여 132,900원에 마감되었습니다. 이번 하락은 코스닥150 정기변경에 따른 수급 우려가 반영된 것으로 보입니다. 특히, 비나텍이 편입 종목에서 제외되면서 투자자들의 매도세가 강화된 것으로 분석됩니다.","content_url":"https://www.edaily.co.kr/news/newspath.asp?newsid=03434166645452856","publisher":"이데일리","polarity":null,"change_rate":-10.81,"created_at":"2026-05-26T14:15:09.000000"},{"code":"126340","date":"2026-05-22","company_name":"비나텍","article_title":"3분기부터 본격 실적 확대 예상…비나텍 18%↑[특징주]","briefing":"비나텍의 주가가 19.10% 상승하여 169,000원에 마감되었습니다. 이 상승은 해외 주요 고객사에 대한 슈퍼캡 셀 독점공급 유지와 하반기 시스템 사업화에 따른 실적 확대 기대감에 기인한 것으로 보입니다. 특히, 3분기부터 본격적인 실적 개선이 예상되며, 이는 투자자들에게 긍정적인 신호로 작용하고 있습니다.","content_url":"https://www.edaily.co.kr/news/newspath.asp?newsid=03309526645451544","publisher":"이데일리","polarity":"긍정","change_rate":19.1,"created_at":"2026-05-22T09:25:00.000000"},{"code":"126340","date":"2026-05-27","company_name":"비나텍","article_title":"비나텍, 증설에 따른 본격 실적 확대 3분기부터…'매수'-DS","briefing":"비나텍의 주가가 5.94% 하락하여 159,900원에 마감되었습니다. 이 하락세는 최근 발표된 실적 확대 기대감에도 불구하고 시장의 전반적인 부정적인 분위기와 관련이 있을 수 있습니다. 주요 이슈로는 코스닥150 편입 종목 발표가 있었으나, 비나텍의 주가는 이에 긍정적인 반응을 보이지 않았습니다.","content_url":"https://www.edaily.co.kr/news/newspath.asp?newsid=02745366645451544","publisher":"이데일리","polarity":"긍정","change_rate":-5.94,"created_at":"2026-05-22T07:47:00.000000"},{"code":"126340","date":"2026-05-21","company_name":"비나텍","article_title":null,"briefing":"비나텍의 주가가 141900.0원으로 -1.46% 하락하였습니다. 이러한 변동에 대한 공식적인 뉴스나 발표는 아직 확인되지 않았습니다.","content_url":null,"publisher":null,"polarity":null,"change_rate":-1.46,"created_at":"2026-05-21"},{"code":"126340","date":"2026-05-20","company_name":"비나텍","article_title":null,"briefing":"비나텍의 주가가 144000.0원으로 4.96% 상승하였습니다. 이러한 변동에 대한 공식적인 뉴스나 발표는 아직 확인되지 않았습니다.","content_url":null,"publisher":null,"polarity":null,"change_rate":4.96,"created_at":"2026-05-20"},{"code":"126340","date":"2026-05-19","company_name":"비나텍","article_title":null,"briefing":"비나텍의 주가가 137200.0원으로 -4.12% 하락하였습니다. 이러한 변동에 대한 공식적인 뉴스나 발표는 아직 확인되지 않았습니다.","content_url":null,"publisher":null,"polarity":null,"change_rate":-4.12,"created_at":"2026-05-19"},{"code":"126340","date":"2026-05-14","company_name":"비나텍","article_title":"저금리 대출창구로 변질 된 CB…'콜옵션 100%'도 등장","briefing":"비나텍의 주가가 3.67% 상승하여 172,300원에 마감되었습니다. 이 상승은 시장에서의 긍정적인 투자 심리와 관련이 있을 것으로 보입니다. 그러나 구체적인 상승 원인에 대한 명확한 이슈는 확인되지 않았습니다.","content_url":"https://www.hankyung.com/article/2026051189901","publisher":"한국경제","polarity":null,"change_rate":3.67,"created_at":"2026-05-11T17:31:00.000000"}]