[{"code":"138360","date":"2026-07-02","company_name":"앤로보틱스","article_title":"앤로보틱스, 中 제니솜로보틱스와 맞손…사족보행로봇 양산 추진","briefing":"앤로보틱스의 주가가 10.02% 하락하여 2,200원에 마감되었습니다. 이번 하락은 중국 제니솜로보틱스와의 전략적 제휴 발표에도 불구하고 시장의 부정적인 반응이 영향을 미친 것으로 보입니다. 제휴 내용이 긍정적임에도 불구하고, 투자자들의 우려가 주가에 부정적인 영향을 미친 것으로 분석됩니다.","content_url":"https://www.mt.co.kr/stock/2026/07/02/2026070209234742326","publisher":"머니투데이","polarity":"긍정","change_rate":-10.02,"created_at":"2026-07-02T09:27:00.000000"},{"code":"138360","date":"2026-07-01","company_name":"앤로보틱스","article_title":null,"briefing":"앤로보틱스의 주가가 2445.0원으로 8.19% 상승하였습니다. 이러한 변동에 대한 공식적인 뉴스나 발표는 아직 확인되지 않았습니다.","content_url":null,"publisher":null,"polarity":null,"change_rate":8.19,"created_at":"2026-07-01"},{"code":"138360","date":"2026-06-30","company_name":"앤로보틱스","article_title":null,"briefing":"앤로보틱스의 주가가 2260.0원으로 9.44% 상승하였습니다. 이러한 변동에 대한 공식적인 뉴스나 발표는 아직 확인되지 않았습니다.","content_url":null,"publisher":null,"polarity":null,"change_rate":9.44,"created_at":"2026-06-30"},{"code":"138360","date":"2026-06-29","company_name":"앤로보틱스","article_title":null,"briefing":"앤로보틱스의 주가가 2065.0원으로 4.66% 상승하였습니다. 이러한 변동에 대한 공식적인 뉴스나 발표는 아직 확인되지 않았습니다.","content_url":null,"publisher":null,"polarity":null,"change_rate":4.66,"created_at":"2026-06-29"},{"code":"138360","date":"2026-06-26","company_name":"앤로보틱스","article_title":null,"briefing":"앤로보틱스의 주가가 1973.0원으로 -3.52% 하락하였습니다. 이러한 변동에 대한 공식적인 뉴스나 발표는 아직 확인되지 않았습니다.","content_url":null,"publisher":null,"polarity":null,"change_rate":-3.52,"created_at":"2026-06-26"},{"code":"138360","date":"2026-06-25","company_name":"앤로보틱스","article_title":null,"briefing":"앤로보틱스의 주가가 2045.0원으로 -3.08% 하락하였습니다. 이러한 변동에 대한 공식적인 뉴스나 발표는 아직 확인되지 않았습니다.","content_url":null,"publisher":null,"polarity":null,"change_rate":-3.08,"created_at":"2026-06-25"},{"code":"138360","date":"2026-06-24","company_name":"앤로보틱스","article_title":null,"briefing":"앤로보틱스의 주가가 2110.0원으로 1.93% 상승하였습니다. 이러한 변동에 대한 공식적인 뉴스나 발표는 아직 확인되지 않았습니다.","content_url":null,"publisher":null,"polarity":null,"change_rate":1.93,"created_at":"2026-06-24"},{"code":"138360","date":"2026-06-23","company_name":"앤로보틱스","article_title":null,"briefing":"앤로보틱스의 주가가 2070.0원으로 -1.43% 하락하였습니다. 이러한 변동에 대한 공식적인 뉴스나 발표는 아직 확인되지 않았습니다.","content_url":null,"publisher":null,"polarity":null,"change_rate":-1.43,"created_at":"2026-06-23"},{"code":"138360","date":"2026-06-22","company_name":"앤로보틱스","article_title":null,"briefing":"앤로보틱스의 주가가 2100.0원으로 -10.64% 하락하였습니다. 이러한 변동에 대한 공식적인 뉴스나 발표는 아직 확인되지 않았습니다.","content_url":null,"publisher":null,"polarity":null,"change_rate":-10.64,"created_at":"2026-06-22"},{"code":"138360","date":"2026-06-19","company_name":"앤로보틱스","article_title":null,"briefing":"앤로보틱스의 주가가 2350.0원으로 -9.62% 하락하였습니다. 이러한 변동에 대한 공식적인 뉴스나 발표는 아직 확인되지 않았습니다.","content_url":null,"publisher":null,"polarity":null,"change_rate":-9.62,"created_at":"2026-06-19"},{"code":"138360","date":"2026-06-18","company_name":"앤로보틱스","article_title":null,"briefing":"앤로보틱스의 주가가 2600.0원으로 3.59% 상승하였습니다. 이러한 변동에 대한 공식적인 뉴스나 발표는 아직 확인되지 않았습니다.","content_url":null,"publisher":null,"polarity":null,"change_rate":3.59,"created_at":"2026-06-18"},{"code":"138360","date":"2026-06-17","company_name":"앤로보틱스","article_title":null,"briefing":"앤로보틱스의 주가가 2510.0원으로 -0.4% 하락하였습니다. 이러한 변동에 대한 공식적인 뉴스나 발표는 아직 확인되지 않았습니다.","content_url":null,"publisher":null,"polarity":null,"change_rate":-0.4,"created_at":"2026-06-17"},{"code":"138360","date":"2026-06-09","company_name":"앤로보틱스","article_title":"앤로보틱스, '서울푸드 2026'서 AI 기반 식품 자동화 성형설비 공개","briefing":"앤로보틱스의 주가가 2.50% 상승하여 2,460.0원에 마감되었습니다. 이번 상승은 '서울푸드 2026' 전시회에서 AI 기반 식품 자동화 성형설비를 공개한 것이 긍정적인 영향을 미친 것으로 보입니다. 이러한 기술 혁신은 향후 식품 생산 자동화 공정의 개선으로 이어질 것으로 기대됩니다.","content_url":"https://www.mt.co.kr/stock/2026/06/09/2026060908433565821","publisher":"머니투데이","polarity":"긍정","change_rate":2.5,"created_at":"2026-06-09T08:57:00.000000"},{"code":"138360","date":"2026-06-08","company_name":"앤로보틱스","article_title":null,"briefing":"앤로보틱스의 주가가 2400.0원으로 -5.33% 하락하였습니다. 이러한 변동에 대한 공식적인 뉴스나 발표는 아직 확인되지 않았습니다.","content_url":null,"publisher":null,"polarity":null,"change_rate":-5.33,"created_at":"2026-06-08"},{"code":"138360","date":"2026-06-05","company_name":"앤로보틱스","article_title":null,"briefing":"앤로보틱스의 주가가 2535.0원으로 2.42% 상승하였습니다. 이러한 변동에 대한 공식적인 뉴스나 발표는 아직 확인되지 않았습니다.","content_url":null,"publisher":null,"polarity":null,"change_rate":2.42,"created_at":"2026-06-05"},{"code":"138360","date":"2026-06-04","company_name":"앤로보틱스","article_title":null,"briefing":"앤로보틱스의 주가가 2475.0원으로 -1.2% 하락하였습니다. 이러한 변동에 대한 공식적인 뉴스나 발표는 아직 확인되지 않았습니다.","content_url":null,"publisher":null,"polarity":null,"change_rate":-1.2,"created_at":"2026-06-04"},{"code":"138360","date":"2026-06-02","company_name":"앤로보틱스","article_title":null,"briefing":"앤로보틱스의 주가가 2505.0원으로 -4.75% 하락하였습니다. 이러한 변동에 대한 공식적인 뉴스나 발표는 아직 확인되지 않았습니다.","content_url":null,"publisher":null,"polarity":null,"change_rate":-4.75,"created_at":"2026-06-02"},{"code":"138360","date":"2026-06-01","company_name":"앤로보틱스","article_title":null,"briefing":"앤로보틱스의 주가가 2630.0원으로 -0.75% 하락하였습니다. 이러한 변동에 대한 공식적인 뉴스나 발표는 아직 확인되지 않았습니다.","content_url":null,"publisher":null,"polarity":null,"change_rate":-0.75,"created_at":"2026-06-01"},{"code":"138360","date":"2026-05-29","company_name":"앤로보틱스","article_title":null,"briefing":"앤로보틱스의 주가가 2650.0원으로 -4.16% 하락하였습니다. 이러한 변동에 대한 공식적인 뉴스나 발표는 아직 확인되지 않았습니다.","content_url":null,"publisher":null,"polarity":null,"change_rate":-4.16,"created_at":"2026-05-29"},{"code":"138360","date":"2026-05-28","company_name":"앤로보틱스","article_title":null,"briefing":"앤로보틱스의 주가가 2765.0원으로 -6.27% 하락하였습니다. 이러한 변동에 대한 공식적인 뉴스나 발표는 아직 확인되지 않았습니다.","content_url":null,"publisher":null,"polarity":null,"change_rate":-6.27,"created_at":"2026-05-28"},{"code":"138360","date":"2026-05-27","company_name":"앤로보틱스","article_title":null,"briefing":"앤로보틱스의 주가가 2950.0원으로 -10.06% 하락하였습니다. 이러한 변동에 대한 공식적인 뉴스나 발표는 아직 확인되지 않았습니다.","content_url":null,"publisher":null,"polarity":null,"change_rate":-10.06,"created_at":"2026-05-27"},{"code":"138360","date":"2026-05-26","company_name":"앤로보틱스","article_title":null,"briefing":"앤로보틱스의 주가가 3280.0원으로 1.55% 상승하였습니다. 이러한 변동에 대한 공식적인 뉴스나 발표는 아직 확인되지 않았습니다.","content_url":null,"publisher":null,"polarity":null,"change_rate":1.55,"created_at":"2026-05-26"},{"code":"138360","date":"2026-05-18","company_name":"앤로보틱스","article_title":"[서울데이터랩]코스닥 거래대금 상위 종목 혼조…로봇·반도체 강세, 일부 개별주는 급락","briefing":"앤로보틱스의 주가가 8.77% 하락하여 3,590원에 마감되었습니다. 이 하락세는 로봇주 전반의 상승세 속에서도 앤로보틱스가 개별적으로 급락한 것으로 보입니다. 전반적인 시장 분위기와는 달리, 앤로보틱스의 주가는 부진한 성과로 인해 투자자들의 우려가 반영된 것으로 해석됩니다.","content_url":"https://www.seoul.co.kr/news/economy/securities/2026/05/15/20260515500114","publisher":"서울신문","polarity":null,"change_rate":-8.77,"created_at":"2026-05-15T12:54:00.000000"},{"code":"138360","date":"2026-05-15","company_name":"앤로보틱스","article_title":"피지컬 AI 모메텀 기대…로봇주 동반 상승","briefing":"앤로보틱스의 주가가 0.51% 상승하여 3,935원에 마감되었습니다. 이 상승은 로봇주 전반에 대한 투자 심리가 개선된 데 기인한 것으로 보입니다. 특히 피지컬 AI 모멘텀에 대한 기대감이 커지면서 로봇 관련 주식들이 동반 상승하는 흐름을 보였습니다.","content_url":"https://www.mt.co.kr/stock/2026/05/15/2026051509314485386","publisher":"머니투데이","polarity":null,"change_rate":0.51,"created_at":"2026-05-15T09:32:00.000000"},{"code":"138360","date":"2026-05-14","company_name":"앤로보틱스","article_title":"24시간 일하는 로봇...앤로보틱스, 배터리 자동교체시스템 상용화","briefing":"앤로보틱스의 주가가 7.11% 상승하여 3,915원에 마감되었습니다. 이 상승은 배터리 자동교체 시스템의 상용화 소식에 힘입은 것으로 보이며, 이는 로봇 운영의 효율성을 크게 향상시킬 것으로 기대됩니다. 이러한 기술 혁신은 다양한 산업에 적용될 가능성을 열어주어 향후 성장에 긍정적인 영향을 미칠 것으로 전망됩니다.","content_url":"https://www.mt.co.kr/stock/2026/05/07/2026050713195422016","publisher":"머니투데이","polarity":"긍정","change_rate":7.11,"created_at":"2026-05-07T15:41:00.000000"}]