[{"code":"194480","date":"2026-06-25","company_name":"데브시스터즈","article_title":"'쿠키런: 모험의 탑' 2주년 업데이트…'달빛술사 쿠키' 등장","briefing":"데브시스터즈의 주가가 2.92% 하락하여 13,620원에 마감되었습니다. 이번 하락은 특별한 외부 요인 없이도 발생했지만, 최근 '쿠키런: 모험의 탑'의 2주년 업데이트와 '쿠키런 카드 게임'의 글로벌 TCG 플랫폼 입점 소식이 있었음을 알 수 있습니다. 이러한 이슈에도 불구하고 주가는 하락세를 보였으며, 시장의 반응이 다소 부정적임을 나타냅니다.","content_url":"https://www.hankyung.com/article/202606258020g","publisher":"한국경제","polarity":null,"change_rate":-2.92,"created_at":"2026-06-25T15:16:00.000000"},{"code":"194480","date":"2026-06-19","company_name":"데브시스터즈","article_title":"[명운 건 IP] 주주 압박 속 '크럼블', 데브시스터즈 반등키 될까","briefing":"데브시스터즈의 주가가 3.54% 하락하여 16,100원에 마감되었습니다. 이번 하락은 1분기 연결 매출이 585억원, 영업손실이 174억원으로 적자 전환한 소식이 영향을 미친 것으로 보입니다. 이러한 실적 부진은 투자자들의 우려를 불러일으키며 주가에 부정적인 영향을 미쳤습니다.","content_url":"https://www.bloter.net/news/articleView.html?idxno=665687","publisher":"블로터","polarity":null,"change_rate":-3.54,"created_at":"2026-06-17T15:30:00.000000"},{"code":"194480","date":"2026-06-12","company_name":"데브시스터즈","article_title":"데브시스터즈, 쿠키런 17주년 맞아 '쿠키런 데이' 연다","briefing":"데브시스터즈의 주가가 4.09% 상승하여 14,500원에 마감되었습니다. 이번 상승은 '쿠키런' 17주년을 기념한 브랜드 캠페인인 '쿠키런 데이'의 진행 소식에 힘입은 것으로 보입니다. 캠페인을 통해 사용자와의 소통을 강화하고, 브랜드 인지도를 높일 것으로 기대됩니다.","content_url":"https://www.ddaily.co.kr/page/view/2026061211265466942","publisher":"디지털데일리","polarity":null,"change_rate":4.09,"created_at":"2026-06-12T11:33:00.000000"},{"code":"194480","date":"2026-06-11","company_name":"데브시스터즈","article_title":"코스피 질주에도 게임주는 역주행… 소액주주 집단행동 확산","briefing":"데브시스터즈의 주가가 0.92% 하락하여 13,930원에 마감되었습니다. 이 하락세는 게임사 소액주주들의 집단행동과 주주환원 정책 요구가 부각되면서 나타난 것으로 보입니다. 주가 부진이 장기화되면서 투자자들의 우려가 커지고 있는 상황입니다.","content_url":"https://biz.chosun.com/it-science/ict/2026/06/11/D5B6BQJCZ5F23JVZ5DMIU2QDXQ/?utm_medium=original&utm_campaign=biz","publisher":"조선비즈","polarity":null,"change_rate":-0.92,"created_at":"2026-06-11T06:01:32.000000"},{"code":"194480","date":"2026-06-09","company_name":"데브시스터즈","article_title":"쿠키런: 킹덤, '비밀조직 스쿱' 에피소드 추가","briefing":"데브시스터즈의 주가가 1.79% 상승하여 14,230원에 마감되었습니다. 이번 상승은 모바일 RPG '쿠키런: 킹덤'의 새로운 업데이트 소식에 긍정적인 반응이 나타난 것으로 보입니다. 그러나 주가 변동률이 3% 미만으로 크지 않았던 점은 유의할 필요가 있습니다.","content_url":"https://n.news.naver.com/mnews/article/236/0000255279?rc=N&ntype=RANKING&sid=105","publisher":"포모스","polarity":null,"change_rate":1.79,"created_at":"2026-06-04T11:16:29.000000"},{"code":"194480","date":"2026-06-02","company_name":"데브시스터즈","article_title":"'주가 폭락' 데브시스터즈, CFO 주관 주주간담회 개최키로","briefing":"데브시스터즈의 주가가 1.02% 상승하여 15,890원에 마감되었습니다. 주가 상승은 주주간담회 개최 결정과 관련된 소식이 긍정적으로 작용했을 가능성이 있습니다. 그러나 전반적으로 주가는 큰 변동이 없었으며, 소액주주들의 집단행동이 지속되고 있다는 점은 주의가 필요합니다.","content_url":"https://www.sidae.com/article/2026060117074484380","publisher":"동행미디어 시대","polarity":"중립","change_rate":1.02,"created_at":"2026-06-01T17:55:02.000000"},{"code":"194480","date":"2026-06-08","company_name":"데브시스터즈","article_title":"'주가 폭락' 데브시스터즈, CFO 주관 주주간담회 개최키로","briefing":"데브시스터즈의 주가가 5.86% 하락하여 13,980원에 마감되었습니다. 주가 하락의 주요 원인은 소액주주들의 집단행동과 주주간담회 개최 결정으로, 이는 주가 하락에 대한 우려를 반영한 것으로 보입니다. 이러한 상황은 투자자들의 신뢰를 저하시킬 수 있으며, 향후 주가에 부정적인 영향을 미칠 가능성이 있습니다.","content_url":"https://www.sidae.com/article/2026060117074484380","publisher":"동행미디어 시대","polarity":null,"change_rate":-5.86,"created_at":"2026-06-01T17:55:00.000000"},{"code":"194480","date":"2026-06-01","company_name":"데브시스터즈","article_title":"데브시스터즈, 국가유산청과 손잡고 쿠키런으로 韓 세계유산 알린다","briefing":"데브시스터즈의 주가가 2.84% 하락하여 15,730원에 마감되었습니다. 이 하락세는 최근 발표된 유네스코 세계유산위원회와의 협력 소식에도 불구하고, 시장의 전반적인 불안감이 작용한 것으로 보입니다. 주요 이슈로는 쿠키런을 활용한 홍보 활동이 예정되어 있으나, 투자자들의 반응이 부정적이었던 것으로 분석됩니다.","content_url":"https://biz.chosun.com/it-science/ict/2026/05/29/GLHBEIRLMBBSVEVZ52YBETSZMQ/?utm_medium=original&utm_campaign=biz","publisher":"조선비즈","polarity":null,"change_rate":-2.84,"created_at":"2026-05-29T23:22:00.000000"},{"code":"194480","date":"2026-05-29","company_name":"데브시스터즈","article_title":"데브시스터즈, 국가유산청과 맞손... 쿠키런으로 한국 세계유산 알린다","briefing":"데브시스터즈의 주가가 0.86% 하락하여 16,190원에 마감되었습니다. 주가는 큰 변동이 없었으나, 국가유산청과의 협력으로 한국 세계유산을 알리는 홍보 캠페인을 진행한다는 소식이 있었습니다. 이러한 활동은 브랜드 이미지 개선에 기여할 수 있으나, 현재 주가에 미치는 영향은 제한적일 것으로 보입니다.","content_url":"https://www.etnews.com/20260529000137","publisher":"전자신문","polarity":null,"change_rate":-0.86,"created_at":"2026-05-29T10:43:00.000000"},{"code":"194480","date":"2026-05-26","company_name":"데브시스터즈","article_title":"주인 바뀌고 무보수 경영까지…게임사 덮친 위기","briefing":"데브시스터즈의 주가가 0.80% 하락하여 17,390원에 마감되었습니다. 주가 하락의 직접적인 원인은 확인되지 않지만, 중견 게임사들의 IP 경쟁력 약화에 대한 우려가 시장에 영향을 미친 것으로 보입니다. 또한, 쿠키런 IP 기반 신작 게임의 필요성이 강조되며 향후 실적에 대한 불확실성이 커지고 있습니다.","content_url":"https://news.bizwatch.co.kr/article/mobile/2026/05/19/0029","publisher":"비즈워치","polarity":null,"change_rate":-0.8,"created_at":"2026-05-26T07:40:00.000000"},{"code":"194480","date":"2026-05-21","company_name":"데브시스터즈","article_title":"“뉴욕 이어 잠실도 터졌다”…‘쿠키런’ 디저트 팝업 흥행","briefing":"데브시스터즈의 주가가 0.06% 하락하여 16,740원에 마감되었습니다. 주가는 큰 변동 없이 안정세를 보였으나, '쿠키런' 디저트 팝업 스토어의 흥행 소식이 있었습니다. 이는 매출 비중의 40%를 차지하며 IP 확장 가능성을 확인한 긍정적인 요소로 평가됩니다.","content_url":"https://www.mydaily.co.kr/page/view/2026051913413109297","publisher":"마이데일리","polarity":null,"change_rate":-0.06,"created_at":"2026-05-19T13:42:00.000000"},{"code":"194480","date":"2026-05-14","company_name":"데브시스터즈","article_title":"무보수 경영·희망퇴직 카드 꺼낸 데브시스터즈, 경영 쇄신 돌입","briefing":"데브시스터즈의 주가가 2.53% 상승하여 19,070원에 마감되었습니다. 주가는 경영 쇄신과 무보수 경영 발표에 따른 긍정적인 반응으로 상승한 것으로 보입니다. 그러나 여전히 신작 부진과 적자 확대 우려가 남아 있어 향후 실적 개선 여부가 주목됩니다.","content_url":"https://www.sportsworldi.com/newsView/20260513510001","publisher":"스포츠월드","polarity":null,"change_rate":2.53,"created_at":"2026-05-13T15:02:00.000000"},{"code":"194480","date":"2026-05-18","company_name":"데브시스터즈","article_title":"데브시스터즈, 1분기 영업손실 174억원…3분기 연속 적자","briefing":"데브시스터즈의 주가가 3.28% 하락하여 17,700원에 마감되었습니다. 이번 하락은 1분기 영업손실이 174억원에 달하며 3분기 연속 적자를 기록한 것에 기인합니다. 경영진의 무보수 경영과 희망퇴직 등 강도 높은 구조 개편이 발표되었으나, 이는 시장의 우려를 해소하기에는 부족했던 것으로 보입니다.","content_url":"https://n.news.naver.com/mnews/article/347/0000193502?rc=N&ntype=RANKING&sid=105","publisher":"데일리e스포츠","polarity":null,"change_rate":-3.28,"created_at":"2026-05-11T17:25:22.000000"}]