[{"code":"215790","date":"2026-06-16","company_name":"이노인스트루먼트","article_title":"[서울데이터랩]코스닥 거래상위 종목 혼조…서산 상한가, 화신정공·JW신약 강세","briefing":"이노인스트루먼트의 주가가 5.91% 상승하여 1,594원에 마감되었습니다. 이 상승은 중소형주 중심의 개별 종목 장세에서 두드러진 성과로, 시장의 긍정적인 투자 심리가 반영된 것으로 보입니다. 특히 외국인 순매수와 프로그램 매수 우위가 주가 상승에 기여한 것으로 분석됩니다.","content_url":"https://www.seoul.co.kr/news/economy/securities/2026/06/16/20260616500152","publisher":"서울신문","polarity":null,"change_rate":5.91,"created_at":"2026-06-16T14:18:00.000000"},{"code":"215790","date":"2026-06-09","company_name":"이노인스트루먼트","article_title":"[서울데이터랩]코스닥 거래상위 종목 희비…화신정공 상한가·HPSP 22% 급등","briefing":"이노인스트루먼트의 주가가 14.53% 상승하여 1,584원에 마감되었습니다. 이 상승은 외국인과 기관의 순매수에 힘입은 것으로 보이며, 이는 투자 심리 회복에 긍정적인 영향을 미쳤습니다. 또한, 코스닥 시장 전반의 반등 흐름이 이노인스트루먼트의 주가 상승에 기여한 것으로 분석됩니다.","content_url":"https://www.seoul.co.kr/news/economy/securities/2026/06/09/20260609500113","publisher":"서울신문","polarity":"긍정","change_rate":14.53,"created_at":"2026-06-09T13:08:00.000000"},{"code":"215790","date":"2026-06-08","company_name":"이노인스트루먼트","article_title":"[서울데이터랩] 코스닥 2.33% 올라 1049.96…외국인·기관 순매수에 강세","briefing":"이노인스트루먼트의 주가가 11.35% 하락하여 1,383원에 마감되었습니다. 이 하락세는 기업의 직접적인 이슈보다는 전체 시장의 변동성에 영향을 받은 것으로 보입니다. 특히, 삼성전자와 SK하이닉스 등 대형주가 약세를 보이며 시장 전반에 부정적인 영향을 미쳤습니다.","content_url":"https://www.seoul.co.kr/news/economy/securities/2026/06/04/20260604500099","publisher":"서울신문","polarity":null,"change_rate":-11.35,"created_at":"2026-06-04T10:02:00.000000"}]