[{"code":"217500","date":"2026-06-23","company_name":"러셀","article_title":"스페이스X, MSCI ESG 평가서 최하위 등급…\"러시아 수준\" 굴욕","briefing":"러셀의 주가가 9.09% 하락하여 1,530원에 마감되었습니다. 이 하락세는 스페이스X의 상장과 관련된 시장의 불확실성으로 인해 투자 심리가 위축된 것으로 분석됩니다. 특히, 스페이스X의 MSCI ESG 평가에서 최하위 등급을 부여받은 점이 부정적인 영향을 미쳤습니다.","content_url":"https://www.edaily.co.kr/news/newspath.asp?newsid=02020486645484344","publisher":"이데일리","polarity":null,"change_rate":-9.09,"created_at":"2026-06-22T08:17:00.000000"},{"code":"217500","date":"2026-06-22","company_name":"러셀","article_title":"서학개미 1.7조 퍼부었던 스페이스X…연이틀 하락, 본전수준으로","briefing":"러셀의 주가가 2.15% 하락하여 1,683원에 마감되었습니다. 이번 하락은 스페이스X의 상장 이후 주가가 급등한 후 조정세를 보인 것으로 해석됩니다. 또한, 주요 지수 편입 기대감이 있지만, 투자자들의 평균 수익률이 본전 수준으로 낮아지면서 시장의 관심이 지수 편입 여부로 이동하고 있습니다.","content_url":"https://www.munhwa.com/article/11596893","publisher":"문화일보","polarity":"중립","change_rate":-2.15,"created_at":"2026-06-20T08:51:00.000000"},{"code":"217500","date":"2026-06-24","company_name":"러셀","article_title":"옵션시장 \"지수 편입·분석보고서 앞둔 스페이스X, 10% 변동\"...204달러까지 오르거나 166달러로 하락","briefing":"러셀의 주가가 4.44% 상승하여 1,598원에 마감되었습니다. 이 상승은 스페이스X의 지수 편입 기대감과 관련된 투자자들의 긍정적인 반응으로 해석됩니다. 스페이스X의 상장 이후 변동성이 커지고 있는 상황에서, 러셀의 주가는 이러한 시장의 흐름에 영향을 받아 상승세를 보인 것으로 보입니다.","content_url":"http://www.fnnews.com/news/202606200523144738","publisher":"파이낸셜뉴스","polarity":"중립","change_rate":4.44,"created_at":"2026-06-20T05:59:00.000000"},{"code":"217500","date":"2026-06-19","company_name":"러셀","article_title":"프랭클린템플턴 \"스페이스X, 러셀1000 비중 0.11%…'묻어두기식' 지수 투자 적합하지 않아\"","briefing":"러셀의 주가가 3.64% 하락하여 1,720원에 마감되었습니다. 이 하락세는 스페이스X의 지수 편입 비중에 대한 우려와 관련된 시장의 불안감이 반영된 것으로 보입니다. 특히, 스페이스X의 상장 이후 주가가 하락하면서 투자자들의 평균 수익률이 본전 수준으로 돌아간 점이 영향을 미쳤습니다.","content_url":"https://view.asiae.co.kr/article/2026061809233367223","publisher":"아시아경제","polarity":"중립","change_rate":-3.64,"created_at":"2026-06-18T09:23:00.000000"},{"code":"217500","date":"2026-06-17","company_name":"러셀","article_title":"주가 급발진 속 ‘폭풍 매수’…스페이스X, 서학개미 블랙홀","briefing":"러셀의 주가가 0.54% 상승하여 1,857원에 마감되었습니다. 이와 같은 소폭 상승은 스페이스X의 상장과 관련된 투자 심리의 영향을 받은 것으로 보입니다. 그러나 주가 변동이 크지 않았던 만큼, 시장의 전반적인 흐름과 관련된 주요 이슈가 존재했음을 알 수 있습니다.","content_url":"https://www.dt.co.kr/article/12068096","publisher":"디지털타임스","polarity":"긍정","change_rate":0.54,"created_at":"2026-06-17T15:42:00.000000"},{"code":"217500","date":"2026-06-18","company_name":"러셀","article_title":"스페이스X 상장 초기 수급 효과…\"테슬라와 타임라인 구분해야\"","briefing":"러셀의 주가가 3.88% 하락하여 1,785.0원에 마감되었습니다. 이 하락은 스페이스X의 상장과 관련된 시장의 불안감이 반영된 것으로 보입니다. 특히, 대형 IPO 기업들의 지수 편입 비중에 대한 우려가 커지면서 투자자들의 심리가 위축된 것으로 분석됩니다.","content_url":"https://www.newsis.com/view/NISX20260617_0003671970","publisher":"뉴시스","polarity":"중립","change_rate":-3.88,"created_at":"2026-06-17T08:42:00.000000"},{"code":"217500","date":"2026-06-12","company_name":"러셀","article_title":"스페이스X 상장에 우주 ETF도 들썩…한 달 새 2조원 몰렸다","briefing":"러셀의 주가가 5.42% 상승하여 1,924원에 마감되었습니다. 이 상승은 스페이스X의 나스닥 상장과 관련된 긍정적인 시장 반응으로 해석됩니다. 스페이스X의 상장으로 인해 우주 산업 관련 ETF에 자금이 몰리고 있으며, 이는 러셀과 같은 관련 기업에도 긍정적인 영향을 미치고 있습니다.","content_url":"http://www.fnnews.com/news/202606121429275534","publisher":"파이낸셜뉴스","polarity":"중립","change_rate":5.42,"created_at":"2026-06-12T15:05:00.000000"},{"code":"217500","date":"2026-06-11","company_name":"러셀","article_title":"[마켓뷰] 중동긴장 고조속 불안한 투심…변동성 장세 지속 전망","briefing":"러셀의 주가가 0.16% 하락하여 1,825원에 마감되었습니다. 이 하락세는 최근 미국의 중동 긴장 고조와 관련된 불안한 투자 심리로 인해 영향을 받은 것으로 보입니다. 또한, 미국 증시의 하락과 국제유가 상승이 러셀의 주가에 부정적인 영향을 미쳤을 것으로 분석됩니다.","content_url":"https://www.yna.co.kr/view/AKR20260611020700008?input=1195m","publisher":"연합뉴스","polarity":"중립","change_rate":-0.16,"created_at":"2026-06-11T07:48:00.000000"},{"code":"217500","date":"2026-06-09","company_name":"러셀","article_title":"스페이스X, MSCI 조기편입 확정…5.8조달러 패시브 자금 매수대기","briefing":"러셀의 주가가 2.10% 상승하여 1,849원에 마감되었습니다. 주가 상승은 스페이스X의 MSCI 지수 조기 편입 가능성에 대한 기대감이 반영된 것으로 보입니다. 그러나 주가 변동률이 3% 미만으로 큰 변화는 없었으며, 시장의 전반적인 분위기와 관련된 주요 이슈가 있었습니다.","content_url":"https://www.news1.kr/world/international-economy/6191542","publisher":"뉴스1","polarity":"중립","change_rate":2.1,"created_at":"2026-06-09T09:58:00.000000"},{"code":"217500","date":"2026-06-08","company_name":"러셀","article_title":"[마켓인사이트] 반도체 급락에 '휘청' 코스피…지지선 시험받나","briefing":"러셀의 주가가 8.54% 하락하여 1,811원에 마감되었습니다. 이번 하락은 F1 관련 뉴스와는 무관하게, 반도체 업종의 급락과 AI 관련주에 대한 불확실성이 시장에 영향을 미친 것으로 보입니다. 특히 필라델피아 반도체 지수가 10.26% 폭락하며 전체 시장에 부정적인 영향을 미쳤습니다.","content_url":"https://www.yna.co.kr/view/AKR20260606022300008?input=1195m","publisher":"연합뉴스","polarity":null,"change_rate":-8.54,"created_at":"2026-06-07T07:00:00.000000"},{"code":"217500","date":"2026-06-10","company_name":"러셀","article_title":"스페이스X, S&P500 신속 편입 불가…나스닥100엔 15일만에 가능","briefing":"러셀의 주가가 1.14% 하락하여 1,828원에 마감되었습니다. 이 하락세는 스페이스X의 상장과 관련된 지수 편입 규정 유지 소식이 영향을 미친 것으로 보입니다. 이러한 결정은 시장의 불확실성을 증가시켜 투자 심리에 부정적인 영향을 미쳤을 것으로 예상됩니다.","content_url":"https://www.mt.co.kr/world/2026/06/05/2026060516115762480","publisher":"머니투데이","polarity":"중립","change_rate":-1.14,"created_at":"2026-06-05T16:18:00.000000"},{"code":"217500","date":"2026-06-05","company_name":"러셀","article_title":"스페이스X, S&P500 조기 편입 무산…\"규칙 예외 없다\"","briefing":"러셀의 주가가 5.04% 하락하여 1,980원에 마감되었습니다. 이 하락은 S&P500 지수의 신규 상장 기업 조기 편입 불허 결정에 따른 것으로 보입니다. 이러한 결정은 스페이스X의 상장에 대한 기대감을 저하시켰으며, 시장 전반에 부정적인 영향을 미쳤습니다.","content_url":"https://www.news1.kr/world/international-economy/6188573","publisher":"뉴스1","polarity":"중립","change_rate":-5.04,"created_at":"2026-06-05T11:11:08.000000"},{"code":"217500","date":"2026-05-29","company_name":"러셀","article_title":"스페이스X 상장하면 ETF가 자동 매수?…‘수십조 패시브 머니’ 몰린다","briefing":"러셀의 주가가 4.36% 하락하여 2,195원에 마감되었습니다. 이 하락세는 미국의 이란 군사공습 소식과 관련된 지정학적 리스크가 시장에 부정적인 영향을 미친 것으로 분석됩니다. 이러한 불안정한 상황은 투자자들의 심리를 위축시켜 주가에 하방 압력을 가한 것으로 보입니다.","content_url":"https://www.hankyung.com/article/202605272001i","publisher":"한국경제","polarity":"중립","change_rate":-4.36,"created_at":"2026-05-29T13:01:00.000000"},{"code":"217500","date":"2026-05-28","company_name":"러셀","article_title":"美, 이란 공습 소식에 비트코인 7만 4000달러 후퇴[코인브리핑]","briefing":"러셀의 주가가 5.56% 하락하여 2,295원에 마감되었습니다. 이 하락세는 미국의 이란 군사 공습 소식이 전해지면서 위험 자산에 대한 선호가 감소한 데 기인한 것으로 보입니다. 이러한 글로벌 정세의 불안정성이 투자 심리에 부정적인 영향을 미쳤다는 분석이 있습니다.","content_url":"https://www.news1.kr/finance/blockchain-fintech/6179830","publisher":"뉴스1","polarity":"중립","change_rate":-5.56,"created_at":"2026-05-28T09:46:00.000000"},{"code":"217500","date":"2026-05-27","company_name":"러셀","article_title":"위험자산 선호 지속…환율, 1500원대 초반에서 출발 전망[외환브리핑]","briefing":"러셀의 주가가 7.43% 하락하여 2,430원에 마감되었습니다. 이 하락세는 최근 외환 시장의 불안정성과 관련이 있으며, 원·달러 환율이 1,500원 초반대에서 출발할 것으로 예상되면서 투자 심리에 부정적인 영향을 미쳤습니다. 또한, 미국 증시의 상승에도 불구하고 국내 증시에서 외국인 자금의 매도세가 지속되며 하방 압력이 우위를 점하고 있는 상황입니다.","content_url":"https://www.edaily.co.kr/news/newspath.asp?newsid=02781446645453184","publisher":"이데일리","polarity":"중립","change_rate":-7.43,"created_at":"2026-05-27T08:16:00.000000"},{"code":"217500","date":"2026-05-22","company_name":"러셀","article_title":"[오늘의 증시]마이크론 4% 급등·다우 최고치…코스피도 '팔천피' 재도전","briefing":"러셀의 주가가 0.75% 상승하여 2,700원에 마감되었습니다. 이와 같은 소폭 상승은 전반적인 증시 분위기와 관련이 있으며, 특히 미국 증시의 상승세가 긍정적인 영향을 미쳤을 것으로 보입니다. 그러나 러셀에 대한 구체적인 긍정적 이슈는 확인되지 않았습니다.","content_url":"https://www.newsis.com/view/NISX20260522_0003640295","publisher":"뉴시스","polarity":"중립","change_rate":0.75,"created_at":"2026-05-22T07:51:26.000000"},{"code":"217500","date":"2026-05-26","company_name":"러셀","article_title":"[마켓뷰] 트럼프 \"내일 이란공격 안 한다\"…시장변동성 잦아드나","briefing":"러셀의 주가가 2.78% 하락하여 2,625원에 마감되었습니다. 이 하락세는 특별한 이유가 없지만, 최근의 시장 변동성과 관련된 여러 이슈들이 영향을 미쳤을 것으로 보입니다. 특히, 미국 증시의 혼조세와 관련된 불확실성이 투자 심리에 부정적인 영향을 미쳤을 가능성이 있습니다.","content_url":"https://www.yna.co.kr/view/AKR20260519023000008?input=1195m","publisher":"연합뉴스","polarity":null,"change_rate":-2.78,"created_at":"2026-05-19T08:17:00.000000"},{"code":"217500","date":"2026-05-21","company_name":"러셀","article_title":"메이저리그를 흥분시킨 ‘어뢰배트’에 숨겨진 과학 [사이언스 브런치]","briefing":"러셀의 주가가 6.35% 상승하여 2,680원에 마감되었습니다. 이 상승은 메이저리그에서의 '어뢰배트'에 대한 연구 결과가 긍정적으로 평가되면서 주목받은 것으로 보입니다. 이러한 기술적 혁신이 러셀의 제품에 대한 기대감을 높여 주가 상승에 기여한 것으로 분석됩니다.","content_url":"https://www.seoul.co.kr/news/plan/science-diverse-story/2026/05/12/20260512500257","publisher":"서울","polarity":null,"change_rate":6.35,"created_at":"2026-05-14T14:01:09.000000"},{"code":"217500","date":"2026-05-14","company_name":"러셀","article_title":"“기름지고 푸짐한 한끼는 잊어주세요”…맥도날드가 ‘한입 크기’ 내놓은 이유는","briefing":"러셀의 주가가 2.80% 하락하여 2,950원에 마감되었습니다. 이번 하락은 특별한 이유가 없지만, 최근 외식업체들의 소용량 메뉴 출시와 관련된 뉴스가 보도되었습니다. 이는 소비자들의 식습관 변화와 관련이 있으며, 외식업계 전반에 영향을 미칠 수 있는 이슈로 주목받고 있습니다.","content_url":"https://www.mk.co.kr/article/12047403","publisher":"매일경제","polarity":"중립","change_rate":-2.8,"created_at":"2026-05-14T11:33:00.000000"}]